opal_security/__init__.py
opal_security/api_client.py
opal_security/api_response.py
opal_security/configuration.py
opal_security/exceptions.py
opal_security/py.typed
opal_security/rest.py
opal_security/api/__init__.py
opal_security/api/access_rules_api.py
opal_security/api/apps_api.py
opal_security/api/bundles_api.py
opal_security/api/configuration_templates_api.py
opal_security/api/events_api.py
opal_security/api/group_bindings_api.py
opal_security/api/groups_api.py
opal_security/api/idp_group_mappings_api.py
opal_security/api/message_channels_api.py
opal_security/api/non_human_identities_api.py
opal_security/api/on_call_schedules_api.py
opal_security/api/owners_api.py
opal_security/api/requests_api.py
opal_security/api/resources_api.py
opal_security/api/sessions_api.py
opal_security/api/tags_api.py
opal_security/api/uars_api.py
opal_security/api/users_api.py
opal_security/models/__init__.py
opal_security/models/access.py
opal_security/models/access_list.py
opal_security/models/access_rule_condition.py
opal_security/models/add_bundle_group_request.py
opal_security/models/add_bundle_resource_request.py
opal_security/models/add_group_resource_request.py
opal_security/models/add_group_user_request.py
opal_security/models/add_resource_nhi_request.py
opal_security/models/add_resource_user_request.py
opal_security/models/app.py
opal_security/models/app_type_enum.py
opal_security/models/app_validation.py
opal_security/models/app_validation_severity_enum.py
opal_security/models/app_validation_status_enum.py
opal_security/models/apps_list.py
opal_security/models/aws_permission_set_metadata.py
opal_security/models/aws_permission_set_metadata_aws_permission_set.py
opal_security/models/bundle.py
opal_security/models/bundle_group.py
opal_security/models/bundle_resource.py
opal_security/models/condition.py
opal_security/models/configuration_template.py
opal_security/models/create_bundle_info.py
opal_security/models/create_configuration_template_info.py
opal_security-1.0.4.dist-info/METADATA
opal_security-1.0.4.dist-info/WHEEL
opal_security-1.0.4.dist-info/top_level.txt
opal_security-1.0.4.dist-info/RECORD
