Metadata-Version: 2.4
Name: opal-security
Version: 1.0.4
Summary: Opal API
Home-page: 
Author: Opal Team
Author-email: hello@opal.dev
Keywords: OpenAPI,OpenAPI-Generator,Opal API
Requires-Dist: urllib3<3.0.0,>=1.25.3
Requires-Dist: python-dateutil>=2.8.2
Requires-Dist: pydantic>=2
Requires-Dist: typing-extensions>=4.7.1
Dynamic: author
Dynamic: author-email
Dynamic: description
Dynamic: description-content-type
Dynamic: keywords
Dynamic: requires-dist
Dynamic: summary
